fluster_py/__init__.py
fluster_py/generated/__init__.py
flusterio-0.1.dist-info/METADATA
flusterio-0.1.dist-info/WHEEL
flusterio-0.1.dist-info/top_level.txt
flusterio-0.1.dist-info/RECORD
