Metadata-Version: 2.4
Name: flusterIo
Version: 0.1
License: MIT
Dynamic: description
Dynamic: license
